palletjack/__init__.py
palletjack/errors.py
palletjack/extract.py
palletjack/load.py
palletjack/transform.py
palletjack/utils.py
palletjack/version.py
ugrc_palletjack-6.0.0.dist-info/licenses/LICENSE
ugrc_palletjack-6.0.0.dist-info/METADATA
ugrc_palletjack-6.0.0.dist-info/WHEEL
ugrc_palletjack-6.0.0.dist-info/entry_points.txt
ugrc_palletjack-6.0.0.dist-info/top_level.txt
ugrc_palletjack-6.0.0.dist-info/zip-safe
ugrc_palletjack-6.0.0.dist-info/RECORD
