Metadata-Version: 2.4
Name: ugrc-palletjack
Version: 6.0.0
Summary: Updating AGOL feature services with data from external tables.
Home-page: https://github.com/agrc/palletjack
Author: Jake Adams, UGRC
Author-email: jdadams@utah.gov
Project-URL: Issue Tracker, https://github.com/agrc/palletjack/issues
Keywords: gis
Classifier: Development Status :: 5 - Production/Stable
Classifier: Intended Audience :: Developers
Classifier: License :: OSI Approved :: MIT License
Classifier: Topic :: Utilities
License-File: LICENSE
Requires-Dist: arcgis<2.5,>=2.3
Requires-Dist: geopandas<1.2,>=0.14
Requires-Dist: geodatasets<=2025.12,>=2023.12
Requires-Dist: pg8000<1.32,>=1.29
Requires-Dist: psycopg2-binary==2.9.*
Requires-Dist: pygsheets==2.0.*
Requires-Dist: pysftp==0.2.9
Requires-Dist: setuptools==80.*
Requires-Dist: paramiko<5.0,>=3.0
Requires-Dist: SQLAlchemy<2.1,>=1.4
Provides-Extra: tests
Requires-Dist: pdoc3<0.12,>=0.10; extra == "tests"
Requires-Dist: pytest-cov<8,>=3; extra == "tests"
Requires-Dist: pytest-instafail~=0.5; extra == "tests"
Requires-Dist: pytest-mock<3.16,>=3.10; extra == "tests"
Requires-Dist: pytest-watch~=4.2; extra == "tests"
Requires-Dist: pytest<10,>=6; extra == "tests"
Requires-Dist: requests-mock==1.*; extra == "tests"
Requires-Dist: ruff==0.*; extra == "tests"
Dynamic: author
Dynamic: author-email
Dynamic: classifier
Dynamic: description
Dynamic: description-content-type
Dynamic: home-page
Dynamic: keywords
Dynamic: license-file
Dynamic: project-url
Dynamic: provides-extra
Dynamic: requires-dist
Dynamic: summary
